aq/__init__.py
aq/engines.py
aq/errors.py
aq/formatters.py
aq/logger.py
aq/parsers.py
aq/prompt.py
aq/select_parser.py
aq/sqlite_util.py
aq/util.py
aq-0.1.1.dist-info/DESCRIPTION.rst
aq-0.1.1.dist-info/METADATA
aq-0.1.1.dist-info/RECORD
aq-0.1.1.dist-info/WHEEL
aq-0.1.1.dist-info/entry_points.txt
aq-0.1.1.dist-info/metadata.json
aq-0.1.1.dist-info/top_level.txt
