Metadata-Version: 2.0
Name: aq
Version: 0.1.1
Summary: Query AWS resources with SQL
Home-page: https://github.com/lebinh/aq
Author: Binh Le
Author-email: lebinh.it@gmail.com
License: MIT
Keywords: aws sql query
Platform: UNKNOWN
Classifier: Development Status :: 3 - Alpha
Classifier: Intended Audience :: Developers
Classifier: License :: OSI Approved :: MIT License
Classifier: Programming Language :: Python :: 2
Classifier: Programming Language :: Python :: 2.6
Classifier: Programming Language :: Python :: 2.7
Classifier: Programming Language :: Python :: 3
Classifier: Programming Language :: Python :: 3.3
Classifier: Programming Language :: Python :: 3.4
Classifier: Programming Language :: Python :: 3.5
Requires-Dist: boto3
Requires-Dist: docopt
Requires-Dist: prompt-toolkit
Requires-Dist: pygments
Requires-Dist: pyparsing
Requires-Dist: six
Requires-Dist: tabulate
Provides-Extra: dev
Provides-Extra: test
